{
  "visa_application_number": "AUTO000503",
  "case_type": "Tourist",
  "visa_type_requested": "Short Stay 60 Days",
  "application_type": "Initial",
  "submission_date": "2025-10-22",
  "intake_location": "George Town FO",
  "applicant_is_minor": false,
  "urgent": false,
  "given_names": "Ibrahim",
  "surname": "Wong",
  "variation_in_birth_certificate": false,
  "gender": "Female",
  "country_of_nationality": "Malaysia",
  "address": {
    "street_number": "5675 Lincoln Jalan",
    "unit_number": "",
    "postal_code": "15083",
    "city": "Kota Kinabalu",
    "state": "Sabah",
    "country": "Malaysia"
  },
  "date_of_birth": {
    "year": 1990,
    "month": 9,
    "day": 14
  },
  "place_of_birth": {
    "city": "George Town",
    "state": "Penang",
    "country": "Malaysia"
  },
  "residency_status_in_country_of_residence": "Permanent Resident",
  "civil_status": "Married",
  "packaged_member_of_eu": false,
  "occupation": "Student"
}