{
  "visa_application_number": "AUTO000552",
  "case_type": "Student Visa",
  "visa_type_requested": "Short Stay 60 Days",
  "application_type": "Initial",
  "submission_date": "2025-10-22",
  "intake_location": "Kota Kinabalu FO",
  "applicant_is_minor": false,
  "urgent": false,
  "given_names": "Siti",
  "surname": "Raj",
  "variation_in_birth_certificate": false,
  "gender": "Other",
  "country_of_nationality": "Malaysia",
  "address": {
    "street_number": "7830 Washington Persiaran",
    "unit_number": "",
    "postal_code": "92508",
    "city": "Kuala Lumpur",
    "state": "Federal Territory of Kuala Lumpur",
    "country": "Malaysia"
  },
  "date_of_birth": {
    "year": 1956,
    "month": 9,
    "day": 14
  },
  "place_of_birth": {
    "city": "Kuching",
    "state": "Sarawak",
    "country": "Malaysia"
  },
  "residency_status_in_country_of_residence": "Temporary Resident",
  "civil_status": "Single",
  "packaged_member_of_eu": false,
  "occupation": "Teacher"
}