{
  "visa_application_number": "AUTO000678",
  "case_type": "Schengen Short Stay",
  "visa_type_requested": "Short Stay 30 Days",
  "application_type": "Initial",
  "submission_date": "2025-10-22",
  "intake_location": "Annaba FO",
  "applicant_is_minor": false,
  "urgent": false,
  "given_names": "Zahra",
  "surname": "Mahmoudi",
  "variation_in_birth_certificate": false,
  "gender": "Other",
  "country_of_nationality": "Algeria",
  "address": {
    "street_number": "7394 Main Rue",
    "unit_number": "",
    "postal_code": "46145",
    "city": "Tiaret",
    "state": "Tiaret Province",
    "country": "Algeria"
  },
  "date_of_birth": {
    "year": 1969,
    "month": 1,
    "day": 4
  },
  "place_of_birth": {
    "city": "Béchar",
    "state": "Béchar Province",
    "country": "Algeria"
  },
  "residency_status_in_country_of_residence": "Citizen",
  "civil_status": "Married",
  "packaged_member_of_eu": false,
  "occupation": "Retail Worker"
}