{
  "visa_application_number": "AUTO000138",
  "case_type": "Schengen Short Stay",
  "visa_type_requested": "Long Stay",
  "application_type": "Initial",
  "submission_date": "2025-10-21",
  "intake_location": "Melbourne FO",
  "applicant_is_minor": false,
  "urgent": false,
  "given_names": "Lee",
  "surname": "Allen",
  "variation_in_birth_certificate": false,
  "gender": "Male",
  "country_of_nationality": "Australia",
  "address": {
    "street_number": "132 Main St",
    "unit_number": "",
    "postal_code": "7258",
    "city": "Adelaide",
    "state": "ACT",
    "country": "Australia"
  },
  "date_of_birth": {
    "year": 2021,
    "month": 10,
    "day": 7
  },
  "place_of_birth": {
    "city": "Brisbane",
    "state": "ACT",
    "country": "Australia"
  },
  "residency_status_in_australia": "Permanent Resident",
  "civil_status": "Single",
  "packaged_member_of_eu": false,
  "occupation": "Manager"
}