{
  "visa_application_number": "AUTO000331",
  "case_type": "Tourist",
  "visa_type_requested": "Short Stay 60 Days",
  "application_type": "Renewal",
  "submission_date": "2025-10-22",
  "intake_location": "Mumbai FO",
  "applicant_is_minor": true,
  "urgent": false,
  "given_names": "Lata",
  "surname": "Kumar",
  "variation_in_birth_certificate": false,
  "gender": "Other",
  "country_of_nationality": "India",
  "address": {
    "street_number": "2629 Park Main Road",
    "unit_number": "",
    "postal_code": "338431",
    "city": "Thane",
    "state": "Maharashtra",
    "country": "India"
  },
  "date_of_birth": {
    "year": 1940,
    "month": 7,
    "day": 29
  },
  "place_of_birth": {
    "city": "Kolkata",
    "state": "West Bengal",
    "country": "India"
  },
  "residency_status_in_country_of_residence": "Citizen",
  "civil_status": "Single",
  "packaged_member_of_eu": false,
  "occupation": "Manager"
}